{"metadata": {"dbt_schema_version": "https://schemas.getdbt.com/dbt/run-results/v4.json", "dbt_version": "1.5.0", "generated_at": "2023-05-27T11:02:35.641887Z", "invocation_id": "2e64c9c6-e78b-40a8-80e1-14527d71bf96", "env": {}}, "results": [{"status": "success", "timing": [{"name": "compile", "started_at": "2023-05-27T11:02:35.171415Z", "completed_at": "2023-05-27T11:02:35.172434Z"}, {"name": "execute", "started_at": "2023-05-27T11:02:35.174525Z", "completed_at": "2023-05-27T11:02:35.174525Z"}], "thread_id": "Thread-1 (worker)", "execution_time": 0.00809025764465332, "adapter_response": {}, "message": null, "failures": null, "unique_id": "seed.jaffle_shop.raw_customers"}, {"status": "success", "timing": [{"name": "compile", "started_at": "2023-05-27T11:02:35.179824Z", "completed_at": "2023-05-27T11:02:35.180846Z"}, {"name": "execute", "started_at": "2023-05-27T11:02:35.182832Z", "completed_at": "2023-05-27T11:02:35.182832Z"}], "thread_id": "Thread-1 (worker)", "execution_time": 0.007054805755615234, "adapter_response": {}, "message": null, "failures": null, "unique_id": "seed.jaffle_shop.raw_orders"}, {"status": "success", "timing": [{"name": "compile", "started_at": "2023-05-27T11:02:35.190549Z", "completed_at": "2023-05-27T11:02:35.191568Z"}, {"name": "execute", "started_at": "2023-05-27T11:02:35.193547Z", "completed_at": "2023-05-27T11:02:35.193547Z"}], "thread_id": "Thread-1 (worker)", "execution_time": 0.0067138671875, "adapter_response": {}, "message": null, "failures": null, "unique_id": "seed.jaffle_shop.raw_payments"}, {"status": "success", "timing": [{"name": "compile", "started_at": "2023-05-27T11:02:35.197545Z", "completed_at": "2023-05-27T11:02:35.204722Z"}, {"name": "execute", "started_at": "2023-05-27T11:02:35.206723Z", "completed_at": "2023-05-27T11:02:35.206723Z"}], "thread_id": "Thread-1 (worker)", "execution_time": 0.01156926155090332, "adapter_response": {}, "message": null, "failures": null, "unique_id": "model.jaffle_shop.stg_customers"}, {"status": "success", "timing": [{"name": "compile", "started_at": "2023-05-27T11:02:35.212551Z", "completed_at": "2023-05-27T11:02:35.216561Z"}, {"name": "execute", "started_at": "2023-05-27T11:02:35.220611Z", "completed_at": "2023-05-27T11:02:35.220611Z"}], "thread_id": "Thread-1 (worker)", "execution_time": 0.012009620666503906, "adapter_response": {}, "message": null, "failures": null, "unique_id": "model.jaffle_shop.stg_orders"}, {"status": "success", "timing": [{"name": "compile", "started_at": "2023-05-27T11:02:35.226555Z", "completed_at": "2023-05-27T11:02:35.229474Z"}, {"name": "execute", "started_at": "2023-05-27T11:02:35.231498Z", "completed_at": "2023-05-27T11:02:35.231498Z"}], "thread_id": "Thread-1 (worker)", "execution_time": 0.008942127227783203, "adapter_response": {}, "message": null, "failures": null, "unique_id": "model.jaffle_shop.stg_payments"}, {"status": "success", "timing": [{"name": "compile", "started_at": "2023-05-27T11:02:35.239850Z", "completed_at": "2023-05-27T11:02:35.251870Z"}, {"name": "execute", "started_at": "2023-05-27T11:02:35.256277Z", "completed_at": "2023-05-27T11:02:35.256277Z"}], "thread_id": "Thread-1 (worker)", "execution_time": 0.020785808563232422, "adapter_response": {}, "message": null, "failures": null, "unique_id": "test.jaffle_shop.not_null_stg_customers_customer_id.e2cfb1f9aa"}, {"status": "success", "timing": [{"name": "compile", "started_at": "2023-05-27T11:02:35.262639Z", "completed_at": "2023-05-27T11:02:35.273638Z"}, {"name": "execute", "started_at": "2023-05-27T11:02:35.276636Z", "completed_at": "2023-05-27T11:02:35.276636Z"}], "thread_id": "Thread-1 (worker)", "execution_time": 0.017009258270263672, "adapter_response": {}, "message": null, "failures": null, "unique_id": "test.jaffle_shop.unique_stg_customers_customer_id.c7614daada"}, {"status": "success", "timing": [{"name": "compile", "started_at": "2023-05-27T11:02:35.281640Z", "completed_at": "2023-05-27T11:02:35.294340Z"}, {"name": "execute", "started_at": "2023-05-27T11:02:35.296349Z", "completed_at": "2023-05-27T11:02:35.297856Z"}], "thread_id": "Thread-1 (worker)", "execution_time": 0.019221067428588867, "adapter_response": {}, "message": null, "failures": null, "unique_id": "test.jaffle_shop.accepted_values_stg_orders_status__placed__shipped__completed__return_pending__returned.080fb20aad"}, {"status": "success", "timing": [{"name": "compile", "started_at": "2023-05-27T11:02:35.303864Z", "completed_at": "2023-05-27T11:02:35.311208Z"}, {"name": "execute", "started_at": "2023-05-27T11:02:35.313210Z", "completed_at": "2023-05-27T11:02:35.313210Z"}], "thread_id": "Thread-1 (worker)", "execution_time": 0.012343883514404297, "adapter_response": {}, "message": null, "failures": null, "unique_id": "test.jaffle_shop.not_null_stg_orders_order_id.81cfe2fe64"}, {"status": "success", "timing": [{"name": "compile", "started_at": "2023-05-27T11:02:35.320209Z", "completed_at": "2023-05-27T11:02:35.326492Z"}, {"name": "execute", "started_at": "2023-05-27T11:02:35.329039Z", "completed_at": "2023-05-27T11:02:35.329039Z"}], "thread_id": "Thread-1 (worker)", "execution_time": 0.012779951095581055, "adapter_response": {}, "message": null, "failures": null, "unique_id": "test.jaffle_shop.unique_stg_orders_order_id.e3b841c71a"}, {"status": "success", "timing": [{"name": "compile", "started_at": "2023-05-27T11:02:35.337076Z", "completed_at": "2023-05-27T11:02:35.343064Z"}, {"name": "execute", "started_at": "2023-05-27T11:02:35.344065Z", "completed_at": "2023-05-27T11:02:35.344065Z"}], "thread_id": "Thread-1 (worker)", "execution_time": 0.012000083923339844, "adapter_response": {}, "message": null, "failures": null, "unique_id": "model.jaffle_shop.customers"}, {"status": "success", "timing": [{"name": "compile", "started_at": "2023-05-27T11:02:35.350066Z", "completed_at": "2023-05-27T11:02:35.356062Z"}, {"name": "execute", "started_at": "2023-05-27T11:02:35.358367Z", "completed_at": "2023-05-27T11:02:35.358367Z"}], "thread_id": "Thread-1 (worker)", "execution_time": 0.011312484741210938, "adapter_response": {}, "message": null, "failures": null, "unique_id": "model.jaffle_shop.orders"}, {"status": "success", "timing": [{"name": "compile", "started_at": "2023-05-27T11:02:35.363653Z", "completed_at": "2023-05-27T11:02:35.372671Z"}, {"name": "execute", "started_at": "2023-05-27T11:02:35.374667Z", "completed_at": "2023-05-27T11:02:35.374667Z"}], "thread_id": "Thread-1 (worker)", "execution_time": 0.015114784240722656, "adapter_response": {}, "message": null, "failures": null, "unique_id": "test.jaffle_shop.accepted_values_stg_payments_payment_method__credit_card__coupon__bank_transfer__gift_card.3c3820f278"}, {"status": "success", "timing": [{"name": "compile", "started_at": "2023-05-27T11:02:35.380562Z", "completed_at": "2023-05-27T11:02:35.386604Z"}, {"name": "execute", "started_at": "2023-05-27T11:02:35.389685Z", "completed_at": "2023-05-27T11:02:35.389685Z"}], "thread_id": "Thread-1 (worker)", "execution_time": 0.011811017990112305, "adapter_response": {}, "message": null, "failures": null, "unique_id": "test.jaffle_shop.not_null_stg_payments_payment_id.c19cc50075"}, {"status": "success", "timing": [{"name": "compile", "started_at": "2023-05-27T11:02:35.394487Z", "completed_at": "2023-05-27T11:02:35.400051Z"}, {"name": "execute", "started_at": "2023-05-27T11:02:35.403047Z", "completed_at": "2023-05-27T11:02:35.403047Z"}], "thread_id": "Thread-1 (worker)", "execution_time": 0.012558221817016602, "adapter_response": {}, "message": null, "failures": null, "unique_id": "test.jaffle_shop.unique_stg_payments_payment_id.3744510712"}, {"status": "success", "timing": [{"name": "compile", "started_at": "2023-05-27T11:02:35.409557Z", "completed_at": "2023-05-27T11:02:35.415556Z"}, {"name": "execute", "started_at": "2023-05-27T11:02:35.418556Z", "completed_at": "2023-05-27T11:02:35.418556Z"}], "thread_id": "Thread-1 (worker)", "execution_time": 0.013968944549560547, "adapter_response": {}, "message": null, "failures": null, "unique_id": "test.jaffle_shop.not_null_customers_customer_id.5c9bf9911d"}, {"status": "success", "timing": [{"name": "compile", "started_at": "2023-05-27T11:02:35.425438Z", "completed_at": "2023-05-27T11:02:35.430438Z"}, {"name": "execute", "started_at": "2023-05-27T11:02:35.432440Z", "completed_at": "2023-05-27T11:02:35.432440Z"}], "thread_id": "Thread-1 (worker)", "execution_time": 0.010947227478027344, "adapter_response": {}, "message": null, "failures": null, "unique_id": "test.jaffle_shop.unique_customers_customer_id.c5af1ff4b1"}, {"status": "success", "timing": [{"name": "compile", "started_at": "2023-05-27T11:02:35.440314Z", "completed_at": "2023-05-27T11:02:35.451311Z"}, {"name": "execute", "started_at": "2023-05-27T11:02:35.455324Z", "completed_at": "2023-05-27T11:02:35.455324Z"}], "thread_id": "Thread-1 (worker)", "execution_time": 0.01985931396484375, "adapter_response": {}, "message": null, "failures": null, "unique_id": "test.jaffle_shop.accepted_values_orders_status__placed__shipped__completed__return_pending__returned.be6b5b5ec3"}, {"status": "success", "timing": [{"name": "compile", "started_at": "2023-05-27T11:02:35.461522Z", "completed_at": "2023-05-27T11:02:35.466544Z"}, {"name": "execute", "started_at": "2023-05-27T11:02:35.470567Z", "completed_at": "2023-05-27T11:02:35.470567Z"}], "thread_id": "Thread-1 (worker)", "execution_time": 0.013224363327026367, "adapter_response": {}, "message": null, "failures": null, "unique_id": "test.jaffle_shop.not_null_orders_amount.106140f9fd"}, {"status": "success", "timing": [{"name": "compile", "started_at": "2023-05-27T11:02:35.477317Z", "completed_at": "2023-05-27T11:02:35.482319Z"}, {"name": "execute", "started_at": "2023-05-27T11:02:35.485326Z", "completed_at": "2023-05-27T11:02:35.485326Z"}], "thread_id": "Thread-1 (worker)", "execution_time": 0.013383150100708008, "adapter_response": {}, "message": null, "failures": null, "unique_id": "test.jaffle_shop.not_null_orders_bank_transfer_amount.7743500c49"}, {"status": "success", "timing": [{"name": "compile", "started_at": "2023-05-27T11:02:35.492326Z", "completed_at": "2023-05-27T11:02:35.496782Z"}, {"name": "execute", "started_at": "2023-05-27T11:02:35.500323Z", "completed_at": "2023-05-27T11:02:35.500323Z"}], "thread_id": "Thread-1 (worker)", "execution_time": 0.01099085807800293, "adapter_response": {}, "message": null, "failures": null, "unique_id": "test.jaffle_shop.not_null_orders_coupon_amount.ab90c90625"}, {"status": "success", "timing": [{"name": "compile", "started_at": "2023-05-27T11:02:35.506313Z", "completed_at": "2023-05-27T11:02:35.512659Z"}, {"name": "execute", "started_at": "2023-05-27T11:02:35.513659Z", "completed_at": "2023-05-27T11:02:35.513659Z"}], "thread_id": "Thread-1 (worker)", "execution_time": 0.011347532272338867, "adapter_response": {}, "message": null, "failures": null, "unique_id": "test.jaffle_shop.not_null_orders_credit_card_amount.d3ca593b59"}, {"status": "success", "timing": [{"name": "compile", "started_at": "2023-05-27T11:02:35.523659Z", "completed_at": "2023-05-27T11:02:35.529089Z"}, {"name": "execute", "started_at": "2023-05-27T11:02:35.531089Z", "completed_at": "2023-05-27T11:02:35.531089Z"}], "thread_id": "Thread-1 (worker)", "execution_time": 0.01343083381652832, "adapter_response": {}, "message": null, "failures": null, "unique_id": "test.jaffle_shop.not_null_orders_customer_id.c5f02694af"}, {"status": "success", "timing": [{"name": "compile", "started_at": "2023-05-27T11:02:35.539091Z", "completed_at": "2023-05-27T11:02:35.545093Z"}, {"name": "execute", "started_at": "2023-05-27T11:02:35.546885Z", "completed_at": "2023-05-27T11:02:35.546885Z"}], "thread_id": "Thread-1 (worker)", "execution_time": 0.0128326416015625, "adapter_response": {}, "message": null, "failures": null, "unique_id": "test.jaffle_shop.not_null_orders_gift_card_amount.413a0d2d7a"}, {"status": "success", "timing": [{"name": "compile", "started_at": "2023-05-27T11:02:35.555037Z", "completed_at": "2023-05-27T11:02:35.560859Z"}, {"name": "execute", "started_at": "2023-05-27T11:02:35.563870Z", "completed_at": "2023-05-27T11:02:35.563870Z"}], "thread_id": "Thread-1 (worker)", "execution_time": 0.013974666595458984, "adapter_response": {}, "message": null, "failures": null, "unique_id": "test.jaffle_shop.not_null_orders_order_id.cf6c17daed"}, {"status": "success", "timing": [{"name": "compile", "started_at": "2023-05-27T11:02:35.590874Z", "completed_at": "2023-05-27T11:02:35.608392Z"}, {"name": "execute", "started_at": "2023-05-27T11:02:35.610391Z", "completed_at": "2023-05-27T11:02:35.610391Z"}], "thread_id": "Thread-1 (worker)", "execution_time": 0.04452824592590332, "adapter_response": {}, "message": null, "failures": null, "unique_id": "test.jaffle_shop.relationships_orders_customer_id__customer_id__ref_customers_.c6ec7f58f2"}, {"status": "success", "timing": [{"name": "compile", "started_at": "2023-05-27T11:02:35.619391Z", "completed_at": "2023-05-27T11:02:35.628390Z"}, {"name": "execute", "started_at": "2023-05-27T11:02:35.630389Z", "completed_at": "2023-05-27T11:02:35.630389Z"}], "thread_id": "Thread-1 (worker)", "execution_time": 0.01900625228881836, "adapter_response": {}, "message": null, "failures": null, "unique_id": "test.jaffle_shop.unique_orders_order_id.fed79b3a6e"}], "elapsed_time": 0.7456543445587158, "args": {"cache_selected_only": false, "write_json": true, "log_format": "text", "introspect": true, "which": "generate", "print": true, "defer": false, "select": [], "fail_fast": true, "favor_state": false, "log_level_file": "debug", "log_level": "info", "log_path": "C:\\Louw\\GitHub\\dbt\\jaffle_shop\\logs", "quiet": false, "warn_error_options": {"include": [], "exclude": []}, "use_colors": true, "printer_width": 80, "populate_cache": true, "static_parser": true, "strict_mode": false, "project_dir": "C:\\Louw\\GitHub\\dbt\\jaffle_shop", "use_colors_file": true, "compile": true, "log_format_file": "text", "enable_legacy_logger": false, "version_check": true, "warn_error": true, "exclude": [], "profiles_dir": "C:\\Users\\lfouc\\.dbt", "macro_debugging": false, "vars": {}, "send_anonymous_usage_stats": false, "debug": true, "partial_parse": true, "indirect_selection": "eager"}}